super_glass_lsp/__init__.py
super_glass_lsp/config.default.yaml
super_glass_lsp/lsp/__init__.py
super_glass_lsp/lsp/custom/__init__.py
super_glass_lsp/lsp/custom/apps/email_client.yaml
super_glass_lsp/lsp/custom/config_definitions.py
super_glass_lsp/lsp/custom/features/__init__.py
super_glass_lsp/lsp/custom/features/_base.py
super_glass_lsp/lsp/custom/features/_commands.py
super_glass_lsp/lsp/custom/features/_debounce.py
super_glass_lsp/lsp/custom/features/_document.py
super_glass_lsp/lsp/custom/features/_feature.py
super_glass_lsp/lsp/custom/features/_subprocess.py
super_glass_lsp/lsp/custom/features/completer.py
super_glass_lsp/lsp/custom/features/diagnoser.py
super_glass_lsp/lsp/custom/features/formatter.py
super_glass_lsp/lsp/custom/features/goto_definition.py
super_glass_lsp/lsp/custom/features/work_done_progress.py
super_glass_lsp/lsp/custom/features/workspace_edit.py
super_glass_lsp/lsp/custom/hub.py
super_glass_lsp/lsp/custom/tests/__init__.py
super_glass_lsp/lsp/custom/tests/e2e/__init__.py
super_glass_lsp/lsp/custom/tests/e2e/_bin/himalaya
super_glass_lsp/lsp/custom/tests/e2e/apps/__init__.py
super_glass_lsp/lsp/custom/tests/e2e/apps/_utils.py
super_glass_lsp/lsp/custom/tests/e2e/apps/email_client/main_test.py
super_glass_lsp/lsp/custom/tests/e2e/apps/email_client/workspace/.gitignore
super_glass_lsp/lsp/custom/tests/e2e/configs/__init__.py
super_glass_lsp/lsp/custom/tests/e2e/configs/black_test.py
super_glass_lsp/lsp/custom/tests/e2e/configs/flake8_test.py
super_glass_lsp/lsp/custom/tests/e2e/configs/fzf_buffer_test.py
super_glass_lsp/lsp/custom/tests/e2e/configs/jq_test.py
super_glass_lsp/lsp/custom/tests/e2e/configs/markdownlint_test.py
super_glass_lsp/lsp/custom/tests/e2e/configs/mypy_test.py
super_glass_lsp/lsp/custom/tests/e2e/configs/workspace/.gitignore
super_glass_lsp/lsp/custom/tests/e2e/test_debounce_e2e.py
super_glass_lsp/lsp/custom/tests/e2e/test_init_config.py
super_glass_lsp/lsp/custom/tests/units/__init__.py
super_glass_lsp-0.7.0.dist-info/METADATA
super_glass_lsp-0.7.0.dist-info/WHEEL
super_glass_lsp-0.7.0.dist-info/entry_points.txt
super_glass_lsp-0.7.0.dist-info/RECORD
