Metadata-Version: 2.1
Name: super-glass-lsp
Version: 0.7.0
Summary: Generic LSP to parse the output of CLI tools, linters, formatters, etc
License: MIT
Author: Thomas Buckley-Houston
Author-email: tom@tombh.co.uk
Requires-Python: >=3.7,<3.12
Classifier: License :: OSI Approved :: MIT License
Classifier: Programming Language :: Python :: 3
Classifier: Programming Language :: Python :: 3.7
Classifier: Programming Language :: Python :: 3.8
Classifier: Programming Language :: Python :: 3.9
Classifier: Programming Language :: Python :: 3.10
Classifier: Programming Language :: Python :: 3.11
Requires-Dist: mergedeep (>=1.3.4,<2.0.0)
Requires-Dist: parse (>=1.19.0,<2.0.0)
Requires-Dist: psutil (>=5.9.3,<6.0.0)
Requires-Dist: pydantic (==1.10.7)
Requires-Dist: pygls (>=0.13.1,<0.14.0)
Requires-Dist: pyyaml (>=6.0,<7.0)
Requires-Dist: single-source (>=0.3.0,<0.4.0)
